odoo/addons/purchase_split_wizard_stock/README.rst
odoo/addons/purchase_split_wizard_stock/__init__.py
odoo/addons/purchase_split_wizard_stock/__manifest__.py
odoo/addons/purchase_split_wizard_stock/i18n/es.po
odoo/addons/purchase_split_wizard_stock/readme/CONTRIBUTORS.md
odoo/addons/purchase_split_wizard_stock/readme/DESCRIPTION.md
odoo/addons/purchase_split_wizard_stock/readme/USAGE.md
odoo/addons/purchase_split_wizard_stock/static/description/icon.png
odoo/addons/purchase_split_wizard_stock/static/description/index.html
odoo/addons/purchase_split_wizard_stock/wizards/__init__.py
odoo/addons/purchase_split_wizard_stock/wizards/purchase_split_wizard.py
odoo/addons/purchase_split_wizard_stock/wizards/purchase_split_wizard_views.xml
odoo_addon_purchase_split_wizard_stock-16.0.1.0.0.1.dist-info/METADATA
odoo_addon_purchase_split_wizard_stock-16.0.1.0.0.1.dist-info/WHEEL
odoo_addon_purchase_split_wizard_stock-16.0.1.0.0.1.dist-info/top_level.txt
odoo_addon_purchase_split_wizard_stock-16.0.1.0.0.1.dist-info/RECORD
